.gitignore
.travis.yml
CHANGES.txt
CONTRIBUTORS.txt
README.rst
bootstrap.py
buildout.cfg
setup.py
tox.ini
hexagonit/__init__.py
hexagonit.recipe.download.egg-info/PKG-INFO
hexagonit.recipe.download.egg-info/SOURCES.txt
hexagonit.recipe.download.egg-info/dependency_links.txt
hexagonit.recipe.download.egg-info/entry_points.txt
hexagonit.recipe.download.egg-info/namespace_packages.txt
hexagonit.recipe.download.egg-info/not-zip-safe
hexagonit.recipe.download.egg-info/requires.txt
hexagonit.recipe.download.egg-info/top_level.txt
hexagonit/recipe/__init__.py
hexagonit/recipe/download/README.txt
hexagonit/recipe/download/__init__.py
hexagonit/recipe/download/tests.py
hexagonit/recipe/download/testdata/package1-1.2.3-final.tar.gz