Metadata-Version: 1.1
Name: hexagonit.recipe.download
Version: 1.7
Summary: zc.buildout recipe for downloading and extracting packages
Home-page: http://github.com/hexagonit/hexagonit.recipe.download
Author: Kai Lautaportti
Author-email: kai.lautaportti@hexagonit.fi
License: ZPL
Keywords: development buildout recipe
Platform: UNKNOWN
Classifier: Framework :: Buildout :: Recipe
Classifier: Framework :: Buildout
Classifier: Intended Audience :: Developers
Classifier: License :: OSI Approved :: Zope Public License
Classifier: Programming Language :: Python :: 2.6
Classifier: Programming Language :: Python :: 2.7
Classifier: Programming Language :: Python :: 3.2
Classifier: Programming Language :: Python :: 3.3
Classifier: Topic :: Software Development :: Build Tools
Classifier: Topic :: Software Development :: Libraries :: Python Modules
